Metadata-Version: 2.1
Name: datadog_lambda
Version: 8.120.0
Summary: The Datadog AWS Lambda Library
Home-page: https://github.com/DataDog/datadog-lambda-python
License: Apache-2.0
Keywords: datadog,aws,lambda,layer
Author: Datadog, Inc.
Author-email: dev@datadoghq.com
Requires-Python: >=3.8.0,<4
Classifier: License :: OSI Approved :: Apache Software License
Classifier: Programming Language :: Python :: 3
Classifier: Programming Language :: Python :: 3.8
Classifier: Programming Language :: Python :: 3.9
Classifier: Programming Language :: Python :: 3.10
Classifier: Programming Language :: Python :: 3.11
Classifier: Programming Language :: Python :: 3.12
Classifier: Programming Language :: Python :: 3.13
Classifier: Programming Language :: Python :: 3.14
Provides-Extra: dev
Requires-Dist: botocore (>=1.34.0,<2.0.0) ; extra == "dev"
Requires-Dist: datadog (>=0.51.0,<1.0.0)
Requires-Dist: ddtrace (>=3.16.2,<3.19.0)
Requires-Dist: flake8 (>=5.0.4,<6.0.0) ; extra == "dev"
Requires-Dist: pytest (>=8.0.0,<9.0.0) ; extra == "dev"
Requires-Dist: pytest-benchmark (>=4.0,<5.0) ; extra == "dev"
Requires-Dist: requests (>=2.22.0,<3.0.0) ; extra == "dev"
Requires-Dist: ujson (>=5.9.0)
Requires-Dist: wrapt (>=1.11.2,<2.0.0)
Project-URL: Repository, https://github.com/DataDog/datadog-lambda-python
